odoo/addons/hr_contract_reference/README.rst
odoo/addons/hr_contract_reference/__init__.py
odoo/addons/hr_contract_reference/__manifest__.py
odoo/addons/hr_contract_reference/data/hr_contract_sequence.xml
odoo/addons/hr_contract_reference/i18n/ar.po
odoo/addons/hr_contract_reference/i18n/cs_CZ.po
odoo/addons/hr_contract_reference/i18n/de.po
odoo/addons/hr_contract_reference/i18n/es.po
odoo/addons/hr_contract_reference/i18n/fi.po
odoo/addons/hr_contract_reference/i18n/fr.po
odoo/addons/hr_contract_reference/i18n/hi_IN.po
odoo/addons/hr_contract_reference/i18n/hr.po
odoo/addons/hr_contract_reference/i18n/hr_contract_reference.pot
odoo/addons/hr_contract_reference/i18n/it.po
odoo/addons/hr_contract_reference/i18n/lt.po
odoo/addons/hr_contract_reference/i18n/nl_NL.po
odoo/addons/hr_contract_reference/i18n/pt_BR.po
odoo/addons/hr_contract_reference/i18n/ro.po
odoo/addons/hr_contract_reference/i18n/sl.po
odoo/addons/hr_contract_reference/models/__init__.py
odoo/addons/hr_contract_reference/models/hr_contract.py
odoo/addons/hr_contract_reference/static/description/icon.png
odoo/addons/hr_contract_reference/views/hr_contract_view.xml
odoo11_addon_hr_contract_reference-11.0.1.0.0.99.dev4.dist-info/METADATA
odoo11_addon_hr_contract_reference-11.0.1.0.0.99.dev4.dist-info/WHEEL
odoo11_addon_hr_contract_reference-11.0.1.0.0.99.dev4.dist-info/top_level.txt
odoo11_addon_hr_contract_reference-11.0.1.0.0.99.dev4.dist-info/RECORD
